ap0dl/__init__.py
ap0dl/__main__.py
ap0dl/core/__init__.py
ap0dl/core/__version__.py
ap0dl/core/cli/__init__.py
ap0dl/core/cli/commands/__init__.py
ap0dl/core/cli/commands/download.py
ap0dl/core/cli/commands/grab.py
ap0dl/core/cli/commands/schedule.py
ap0dl/core/cli/commands/search.py
ap0dl/core/cli/commands/stream.py
ap0dl/core/cli/commands/update.py
ap0dl/core/cli/exit_codes.py
ap0dl/core/cli/helpers/__init__.py
ap0dl/core/cli/helpers/aniskip.py
ap0dl/core/cli/helpers/banner.py
ap0dl/core/cli/helpers/constants.py
ap0dl/core/cli/helpers/decorators.py
ap0dl/core/cli/helpers/fuzzysearch.py
ap0dl/core/cli/helpers/intelliq.py
ap0dl/core/cli/helpers/logger.py
ap0dl/core/cli/helpers/player.py
ap0dl/core/cli/helpers/players/__init__.py
ap0dl/core/cli/helpers/players/android.py
ap0dl/core/cli/helpers/players/base_player.py
ap0dl/core/cli/helpers/players/ffplay.py
ap0dl/core/cli/helpers/players/mpv.py
ap0dl/core/cli/helpers/players/vlc.py
ap0dl/core/cli/helpers/processors.py
ap0dl/core/cli/helpers/prompts.py
ap0dl/core/cli/helpers/rpc.py
ap0dl/core/cli/helpers/searcher.py
ap0dl/core/cli/helpers/special.py
ap0dl/core/cli/helpers/stream_handlers.py
ap0dl/core/cli/http_client.py
ap0dl/core/codebase/__init__.py
ap0dl/core/codebase/downloader/__init__.py
ap0dl/core/codebase/downloader/ffmpeg.py
ap0dl/core/codebase/downloader/handle.py
ap0dl/core/codebase/downloader/hls.py
ap0dl/core/codebase/downloader/idmanlib.py
ap0dl/core/codebase/extractors/__init__.py
ap0dl/core/codebase/extractors/dailymotion/__init__.py
ap0dl/core/codebase/extractors/doodstream/__init__.py
ap0dl/core/codebase/extractors/gogoplay/__init__.py
ap0dl/core/codebase/extractors/mp4upload/__init__.py
ap0dl/core/codebase/extractors/mycloud/__init__.py
ap0dl/core/codebase/extractors/okru/__init__.py
ap0dl/core/codebase/extractors/rapidvideo/__init__.py
ap0dl/core/codebase/extractors/rapidvideo/polling.py
ap0dl/core/codebase/extractors/rapidvideo/utils.py
ap0dl/core/codebase/extractors/streamlare/__init__.py
ap0dl-1.6.0.dist-info/LICENSE
ap0dl-1.6.0.dist-info/METADATA
ap0dl-1.6.0.dist-info/WHEEL
ap0dl-1.6.0.dist-info/entry_points.txt
ap0dl-1.6.0.dist-info/RECORD
